<Properties StartupConfiguration="{15849EC6-4DB7-4F7C-8B42-3D28C900C88A}|Default">
  <MonoDevelop.Ide.Workbench ActiveDocument="API/Helpers/MappingProfiles.cs">
    <Files>
      <File FileName="API/Controllers/AccountController.cs" Line="61" Column="1" />
      <File FileName="Core/Entities/Identity/Address.cs" Line="13" Column="44" />
      <File FileName="API/DTOs/UserDto.cs" />
      <File FileName="API/DTOs/LoginDto.cs" />
      <File FileName="API/Program.cs" Line="1" Column="1" />
      <File FileName="API/Startup.cs" Line="74" Column="37" />
      <File FileName="API/DTOs/RegisterDto.cs" Line="8" Column="31" />
      <File FileName="Core/Interfaces/ITokenService.cs" Line="8" Column="42" />
      <File FileName="Infrastructure/Services/TokenService.cs" Line="46" Column="51" />
      <File FileName="API/Extensions/IdenityServiceExtensions.cs" Line="32" Column="49" />
      <File FileName="API/appsettings.Development.json" Line="20" Column="2" />
      <File FileName="API/Controllers/BuggyController.cs" Line="21" Column="35" />
      <File FileName="API/Extensions/UserManagerExtensions.cs" Line="13" Column="34" />
      <File FileName="API/DTOs/AddressDto.cs" Line="11" Column="44" />
      <File FileName="API/Helpers/MappingProfiles.cs" Line="1" Column="1" />
    </Files>
    <Pads>
      <Pad Id="ProjectPad">
        <State name="__root__">
          <Option id="ShowAllFiles" value="True" />
          <Node name="sportscom" expanded="True">
            <Node name="Solution Items" expanded="True" />
            <Node name="API" expanded="True">
              <Node name="Controllers" expanded="True" />
              <Node name="DTOs" expanded="True" />
              <Node name="Extensions" expanded="True" />
              <Node name="Helpers" expanded="True">
                <Node name="MappingProfiles.cs" selected="True" />
              </Node>
              <Node name="appsettings.json" expanded="True" />
            </Node>
            <Node name="Core" expanded="True">
              <Node name="Entities" expanded="True">
                <Node name="Identity" expanded="True" />
              </Node>
              <Node name="Interfaces" expanded="True" />
            </Node>
            <Node name="Infrastructure" expanded="True">
              <Node name="Services" expanded="True" />
            </Node>
          </Node>
        </State>
      </Pad>
    </Pads>
  </MonoDevelop.Ide.Workbench>
  <MonoDevelop.Ide.ItemProperties.API PreferredExecutionTarget="/Applications/Safari.app" />
  <MonoDevelop.Ide.DebuggingService.PinnedWatches />
  <MonoDevelop.Ide.Workspace ActiveConfiguration="Debug" />
  <MonoDevelop.Ide.DebuggingService.Breakpoints>
    <BreakpointStore>
      <Breakpoint file="/Users/aneta/Projects/Shop/sportscom/API/Controllers/BaseApiController.cs" relfile="API/Controllers/BaseApiController.cs" line="10" column="1" />
      <Breakpoint file="/Users/aneta/Projects/Shop/sportscom/API/Controllers/ErrorController.cs" relfile="API/Controllers/ErrorController.cs" line="16" column="1" />
      <Breakpoint file="/Users/aneta/Projects/Shop/sportscom/API/Controllers/BuggyController.cs" relfile="API/Controllers/BuggyController.cs" line="39" column="1" />
      <Breakpoint file="/Users/aneta/Projects/Shop/sportscom/API/Controllers/BuggyController.cs" relfile="API/Controllers/BuggyController.cs" line="28" column="1" />
      <Breakpoint file="/Users/aneta/Projects/Shop/sportscom/API/Controllers/BuggyController.cs" relfile="API/Controllers/BuggyController.cs" line="15" column="1" />
      <Breakpoint file="/Users/aneta/Projects/Shop/sportscom/API/Controllers/BuggyController.cs" relfile="API/Controllers/BuggyController.cs" line="47" column="1" />
      <Breakpoint file="/Users/aneta/Projects/Shop/sportscom/Infrastructure/Data/ProductRepository.cs" relfile="Infrastructure/Data/ProductRepository.cs" line="33" column="1" />
      <Breakpoint file="/Users/aneta/Projects/Shop/sportscom/Core/Specifications/ProductWithFiltersForCountSpecification.cs" relfile="Core/Specifications/ProductWithFiltersForCountSpecification.cs" line="9" column="1" />
      <Breakpoint file="/Users/aneta/Projects/Shop/sportscom/Core/Specifications/ProductsWithTypesAndBrandsSpecification.cs" relfile="Core/Specifications/ProductsWithTypesAndBrandsSpecification.cs" line="11" column="1" />
      <Breakpoint file="/Users/aneta/Projects/Shop/sportscom/API/Program.cs" relfile="API/Program.cs" line="30" column="1" />
      <Breakpoint file="/Users/aneta/Projects/Shop/sportscom/Infrastructure/Identity/AppIdentityDbContext.cs" relfile="Infrastructure/Identity/AppIdentityDbContext.cs" line="20" column="1" />
    </BreakpointStore>
  </MonoDevelop.Ide.DebuggingService.Breakpoints>
  <MultiItemStartupConfigurations />
</Properties>